{"cameraMode":{"drawMode":0,"name":"Shaded","section":"Shading Mode"},"sceneLighting":false,"audioPlay":false,"sceneViewState":{"m_AlwaysRefresh":false,"showFog":true,"showSkybox":false,"showFlares":true,"showImageEffects":true,"showParticleSystems":true,"showVisualEffectGraphs":true,"m_FxEnabled":true},"in2DMode":false,"pivot":{"x":13.153019905090332,"y":8.132355690002442,"z":4.241656303405762},"rotation":{"x":-0.21109965443611146,"y":0.7887930870056152,"z":0.4007810354232788,"w":0.41547513008117678},"size":1.149099349975586,"orthographic":false}